originpro/__init__.py
originpro/analysis.py
originpro/base.py
originpro/config.py
originpro/dc.py
originpro/graph.py
originpro/image.py
originpro/imp.py
originpro/matrix.py
originpro/notes.py
originpro/pe.py
originpro/project.py
originpro/utils.py
originpro/worksheet.py
originpro-1.1.14.data/data/LICENSE.txt
originpro-1.1.14.dist-info/LICENSE.txt
originpro-1.1.14.dist-info/METADATA
originpro-1.1.14.dist-info/WHEEL
originpro-1.1.14.dist-info/top_level.txt
originpro-1.1.14.dist-info/RECORD
