Metadata-Version: 2.2
Name: originpro
Version: 1.1.14
Summary: OriginPro Utilities
Home-page: https://www.originlab.com
Author: OriginLab
Author-email: tech@originlab.com
License: BSD
Keywords: Origin,Originlab
Platform: Windows
Classifier: Programming Language :: Python :: 3
Classifier: License :: OSI Approved :: BSD License
Requires-Python: >=3.8
License-File: LICENSE.txt
Requires-Dist: OriginExt>=1.2.5
Dynamic: author
Dynamic: author-email
Dynamic: classifier
Dynamic: description
Dynamic: description-content-type
Dynamic: home-page
Dynamic: keywords
Dynamic: license
Dynamic: platform
Dynamic: requires-dist
Dynamic: requires-python
Dynamic: summary
